{
  "id": "eae6b4cd-cafe-4c07-9b4d-0a3f29267466",
  "quelle_id": "GradualeTriplex",
  "dokumenten_id": "GrTr 493",
  "gattung1": "Introitus",
  "gattung2": "",
  "festtag": "",
  "feier": "",
  "textinitium": "In medio ecclesiae",
  "bibliographischerverweis": "GrTr 493",
  "druckausgabe": "",
  "zeilenstart": "",
  "foliostart": "",
  "kommentar": "",
  "editionsstatus": "ediert",
  "additionalData": {
    "Melodiennummer_Katalog": "",
    "Editor": "sandaanna@gmail.com",
    "iiifs": "",
    "Bezugsgesang": "",
    "Melodie_Standard": "–",
    "Endseite": "",
    "Startposition": "",
    "Zusatz_zu_Textinitium": "",
    "Referenz_auf_Spiel": "",
    "Endzeile": "",
    "Nachtragsschicht": "",
    "Überlieferungszustand": "",
    "Melodie_Quelle": ""
  },
  "publish": "meta-and-notes"
}